{
    "name": "AnimalCio",
    "fields": [
        {
            "fieldName": "dataDoCio",
            "fieldType": "LocalDate"
        },
        {
            "fieldName": "observacao",
            "fieldType": "byte[]",
            "fieldTypeBlobContent": "text"
        }
    ],
    "relationships": [
        {
            "relationshipType": "many-to-one",
            "otherEntityName": "animal",
            "otherEntityRelationshipName": "animalCio",
            "relationshipName": "animal",
            "otherEntityField": "id"
        }
    ],
    "changelogDate": "20200226230301",
    "entityTableName": "animal_cio",
    "dto": "mapstruct",
    "pagination": "pagination",
    "service": "serviceClass",
    "jpaMetamodelFiltering": true,
    "fluentMethods": true,
    "readOnly": false,
    "clientRootFolder": "",
    "applications": "*"
}